vjmap_py_client/__init__.py
vjmap_py_client/client.py
vjmap_py_client/utils.py
vjmap_py_client-0.1.4.dist-info/LICENSE
vjmap_py_client-0.1.4.dist-info/METADATA
vjmap_py_client-0.1.4.dist-info/WHEEL
vjmap_py_client-0.1.4.dist-info/top_level.txt
vjmap_py_client-0.1.4.dist-info/RECORD
