Metadata-Version: 2.1
Name: vjmap-py-client
Version: 0.1.4
Summary: A package for interacting with the Vjmap Service-API
Home-page: https://github.com/twisker/vjmap-py-client
Author: Neo Wang
Author-email: wang.neo@gmail.com
License: MIT
Keywords: vjmap cad python sdk client
Classifier: Programming Language :: Python :: 3
Classifier: License :: OSI Approved :: MIT License
Classifier: Operating System :: OS Independent
Requires-Python: >=3.6
License-File: LICENSE
Requires-Dist: requests
